<?xml version="1.0" encoding="UTF-8"?>
<list xmlns:xsi="http://www.w3.org/2001/XMLSchema-instance" xsi:noNamespaceSchemaLocation="../../xsd/items.xsd">
	<item id="94303" name="Life Stone - Heroic Circlet" type="EtcItem">
		<!-- Can augment Heroic Circlet when used. Augmentation Fee: Adena -->
		<set name="icon" val="Icon.bm_mineral_circlet_hair_acc" />
		<set name="immediate_effect" val="true" />
		<set name="material" val="LIQUID" />
		<set name="weight" val="2" />
		<set name="is_sellable" val="false" />
		<set name="is_stackable" val="true" />
	</item>
	<item id="94304" name="Life Stone - Heroic Circlet" additionalName="Event" type="EtcItem">
		<!-- Can augment Heroic Circlet when used. Augmentation Fee: Adena -->
		<set name="icon" val="Icon.bm_mineral_circlet_hair_acc" />
		<set name="immediate_effect" val="true" />
		<set name="material" val="LIQUID" />
		<set name="weight" val="2" />
		<set name="is_tradable" val="false" />
		<set name="is_dropable" val="false" />
		<set name="is_sellable" val="false" />
		<set name="is_stackable" val="true" />
	</item>
	<item id="94314" name="Elixir" type="EtcItem">
		<!-- A potion containing a mysterious power. <Effect>. Points Ability +1. For characters level 76 or higher. Can use up to 5 -->
		<set name="icon" val="icon.giant_blue_potion" />
		<set name="default_action" val="SKILL_REDUCE" />
		<set name="immediate_effect" val="true" />
		<set name="is_tradable" val="false" />
		<set name="is_dropable" val="false" />
		<set name="is_sellable" val="false" />
		<set name="is_stackable" val="true" />
		<set name="is_oly_restricted" val="true" />
		<set name="material" val="PAPER" />
		<set name="handler" val="Elixir" />
		<set name="is_event_restricted" val="true" />
		<set name="for_npc" val="true" />
		<skills>
			<skill id="40225" level="1" /> <!-- Elixir -->
		</skills>
	</item>
	<item id="94328" name="Elixir Powder" type="EtcItem">
		<!-- Powder that has the power of eternal youth and immortality. Crafting ingredient for Elixir. -->
		<set name="icon" val="icon.etc_powder_of_life_i01" />
		<set name="material" val="PAPER" />
		<set name="is_tradable" val="false" />
		<set name="is_dropable" val="false" />
		<set name="is_sellable" val="false" />
		<set name="is_stackable" val="true" />
	</item>
	<item id="94341" name="Special Buff Scroll" type="EtcItem">
		<!-- Remains for 24 hours when used. Special reward given every hour. - All Stats +1. Protected at death -->
		<set name="icon" val="icon.etc_training_scroll_kalie_i00" />
		<set name="default_action" val="SKILL_REDUCE" />
		<set name="immediate_effect" val="true" />
		<set name="material" val="PAPER" />
		<set name="is_tradable" val="false" />
		<set name="is_dropable" val="false" />
		<set name="is_sellable" val="false" />
		<set name="is_stackable" val="true" />
	</item>
	<item id="94359" name="For Monster only (Crossbow)" type="Weapon">
		<!-- Monster weapon. Bow -->
		<set name="icon" val="icon.weapon_monster_i00" />
		<set name="default_action" val="EQUIP" />
		<set name="weapon_type" val="DAGGER" />
		<set name="immediate_effect" val="true" />
		<set name="crystal_type" val="D" />
		<set name="material" val="STEEL" />
		<set name="weight" val="181" />
		<set name="mp_consume" val="2" />
		<set name="is_dropable" val="false" />
		<set name="is_sellable" val="false" />
		<set name="is_freightable" val="true" />
		<set name="bodypart" val="lrhand" />
		<set name="soulshots" val="1" />
		<set name="spiritshots" val="1" />
		<stats>
			<stat type="pAtk">31</stat>
			<stat type="mAtk">21</stat>
			<stat type="rCrit">8</stat>
			<stat type="pAtkSpd">379</stat>
			<stat type="pAtkRange">80</stat>
			<stat type="randomDamage">5</stat>
		</stats>
	</item>
	<item id="94375" name="Daily Consumables Cube - 30 Times" additionalName="For Aden" type="EtcItem">
		<!-- Use to obtain the following items. <Guaranteed>. Sayha's Blessing: 20. Spirit Ore: 500. Soulshot Ticket: 10. <Can be used once a day>. <Can be used a total of 30 times>. <Bonus Item on 30th time: Blessed/Cursed Enchant Scroll Pack> -->
		<set name="icon" val="icon.sa_cube" />
		<set name="immediate_effect" val="true" />
		<set name="material" val="PAPER" />
		<set name="is_tradable" val="false" />
		<set name="is_dropable" val="false" />
		<set name="is_sellable" val="false" />
	</item>
	<item id="94378" name="Daily Consumables Cube - 10 Times" additionalName="For Aden" type="EtcItem">
		<!-- Use to obtain the following items. <Guaranteed>. Sayha's Blessing: 20. Spirit Ore: 500. Soulshot Ticket: 10. <Can be used once a day>. <Can be used a total of 10 times> -->
		<set name="icon" val="icon.special_cube_i00" />
		<set name="immediate_effect" val="true" />
		<set name="material" val="PAPER" />
		<set name="is_tradable" val="false" />
		<set name="is_dropable" val="false" />
		<set name="is_sellable" val="false" />
	</item>
</list>
