<?xml version="1.0" encoding="UTF-8"?>
<list xmlns:xsi="http://www.w3.org/2001/XMLSchema-instance" xsi:noNamespaceSchemaLocation="../../../xsd/optionsData.xsd">
	<option id="33300" name="option_id_33300">
	</option>
	<option id="33301" name="option_id_33301">
	</option>
	<option id="33302" name="option_id_33302">
	</option>
	<option id="33303" name="option_id_33303">
	</option>
	<option id="33304" name="option_id_33304">
	</option>
	<option id="33305" name="option_id_33305">
	</option>
	<option id="33306" name="option_id_33306">
	</option>
	<option id="33307" name="option_id_33307">
	</option>
	<option id="33308" name="option_id_33308">
	</option>
	<option id="33309" name="option_id_33309">
	</option>
	<option id="33310" name="option_id_33310">
	</option>
	<option id="33311" name="option_id_33311">
	</option>
	<option id="33312" name="option_id_33312">
	</option>
	<option id="33313" name="option_id_33313">
	</option>
	<option id="33314" name="option_id_33314">
	</option>
	<option id="33315" name="option_id_33315">
	</option>
	<option id="33316" name="option_id_33316">
	</option>
	<option id="33317" name="option_id_33317">
	</option>
	<option id="33318" name="option_id_33318">
	</option>
	<option id="33319" name="option_id_33319">
	</option>
	<option id="33320" name="option_id_33320">
	</option>
	<option id="33321" name="option_id_33321">
	</option>
	<option id="33322" name="option_id_33322">
	</option>
	<option id="33323" name="option_id_33323">
	</option>
	<option id="33324" name="option_id_33324">
	</option>
	<option id="33325" name="Special Sayha's Cloak">
		<!-- Max HP/MP +15%, XP/SP Gain +30%, P. Def. +11%, P. Critical/M. Skill Critical Damage +15%, M. Def. +6%, P. Critical/M. Skill Critical Damage Received -10% -->
		<passive_skill id="54044" level="1" /> <!-- Sayha's Supreme Cloak -->
	</option>
	<option id="33326" name="Special Sayha's Cloak">
		<!-- Max HP/MP +15%, XP/SP Gain +30%, P. Def. +12%, P. Critical Damage +15%, M. Skill Critical Damage +16%, M. Def. +8%, P. Critical/M. Skill Critical Damage Received -10% -->
		<passive_skill id="54045" level="1" /> <!-- Sayha's Supreme Cloak +1 -->
	</option>
	<option id="33327" name="Special Sayha's Cloak">
		<!-- Max HP/MP +15%, XP/SP Gain +30%, P. Def. +13%, P. Critical Damage +15%, M. Skill Critical Damage +16%, M. Def. +10%, P. Critical/M. Skill Critical Damage Received -10% -->
		<passive_skill id="54045" level="2" /> <!-- Sayha's Supreme Cloak +2 -->
	</option>
	<option id="33328" name="Special Sayha's Cloak">
		<!-- Max HP/MP +17%, XP/SP Gain +30%, P. Def. +14%, P. Critical Damage +15%, M. Skill Critical Damage +17%, M. Def. +12%, P. Critical/M. Skill Critical Damage Received -10% -->
		<passive_skill id="54045" level="3" /> <!-- Sayha's Supreme Cloak +3 -->
	</option>
	<option id="33329" name="Special Sayha's Cloak">
		<!-- Max HP/MP +17%, XP/SP Gain +30%, P. Def. +15%, P. Critical Damage +16%, M. Skill Critical Damage +17%, M. Def. +14%, P. Critical/M. Skill Critical Damage Received -10% -->
		<passive_skill id="54045" level="4" /> <!-- Sayha's Supreme Cloak +4 -->
	</option>
	<option id="33330" name="Special Sayha's Cloak">
		<!-- Max HP/MP +17%, XP/SP Gain +30%, P. Def. +16%, P. Critical Damage +16%, M. Skill Critical Damage +18%, M. Def. +16%, P. Critical/M. Skill Critical Damage Received -11% -->
		<passive_skill id="54045" level="5" /> <!-- Sayha's Supreme Cloak +5 -->
	</option>
	<option id="33331" name="Special Sayha's Cloak">
		<!-- Max HP/MP +20%, XP/SP Gain +30%, P. Def. +17%, P. Critical Damage +16%, M. Skill Critical Damage +18%, M. Def. +17%, P. Critical/M. Skill Critical Damage Received -11%, PvE Damage +2%, PvP Damage +1% -->
		<passive_skill id="54045" level="6" /> <!-- Sayha's Supreme Cloak +6 -->
	</option>
	<option id="33332" name="Special Sayha's Cloak">
		<!-- Max HP/MP +20%, XP/SP Gain +30%, P. Def. +18%, P. Critical Damage +17%, M. Skill Critical Damage +19%, M. Def. +18%, P. Critical/M. Skill Critical Damage Received -11%, PvE Damage +3%, PvP Damage +2% -->
		<passive_skill id="54045" level="7" /> <!-- Sayha's Supreme Cloak +7 -->
	</option>
	<option id="33333" name="Special Sayha's Cloak">
		<!-- Max HP/MP +21%, XP/SP Gain +30%, P. Def. +19%, P. Critical Damage +17%, M. Skill Critical Damage +20%, M. Def. +19%, P. Critical/M. Skill Critical Damage Received -12%, PvE Damage +5%, PvP Damage +3% -->
		<passive_skill id="54045" level="8" /> <!-- Sayha's Supreme Cloak +8 -->
	</option>
	<option id="33334" name="Special Sayha's Cloak">
		<!-- Max HP/MP +22%, XP/SP Gain +30%, P. Def. +20%, P. Critical Damage +18%, M. Skill Critical Damage +21%, M. Def. +20%, P. Critical/M. Skill Critical Damage Received -13%, PvE Damage +7%, PvP Damage +4% -->
		<passive_skill id="54045" level="9" /> <!-- Sayha's Supreme Cloak +9 -->
	</option>
	<option id="33335" name="Special Sayha's Cloak">
		<!-- Max HP/MP +25%, XP/SP Gain +30%, P. Def. +25%, P. Critical Damage +20%, M. Skill Critical Damage +25%, M. Def. +25%, P. Critical/M. Skill Critical Damage Received -15%, PvE Damage +10%, PvP Damage +5% -->
		<passive_skill id="54045" level="10" /> <!-- Sayha's Supreme Cloak +10 -->
	</option>
	<option id="33336" name="Special Sayha's Cloak">
		<!-- Sayha Blink: Cancels target and teleports to the back -->
		<passive_skill id="54040" level="1" /> <!-- Sayha's Blink -->
	</option>
	<option id="33337" name="Rapid Wind">
		<!-- Rapid Wind: For 5 sec., P. Def. +1000, M. Def. +1000, Speed +50 -->
		<active_skill id="54043" level="1" /> <!-- Rapid Wind -->
	</option>
	<option id="33338" name="Talisman of Aden">
		<passive_skill id="54047" level="1" /> <!-- Talisman: Aden Talisman -->
	</option>
	<option id="33339" name="Talisman of Aden">
		<!-- P. Def. +5\nM. Def. +5\nAtk. Spd. +10\nCasting Spd. +10\nMax HP +100\nMax MP +30. -->
		<passive_skill id="54047" level="2" /> <!-- Talisman: Aden Talisman +1 -->
	</option>
	<option id="33340" name="Talisman of Aden">
		<!-- P. Def. +10\nM. Def. +10\nAtk. Spd. +12\nCasting Spd. +12\nMax HP +120\nMax MP +50. -->
		<passive_skill id="54047" level="3" /> <!-- Talisman: Aden Talisman +2 -->
	</option>
	<option id="33341" name="Talisman of Aden">
		<!-- P. Def. +15\nM. Def. +20\nAtk. Spd. +15\nCasting Spd. +15\nMax HP +150\nMax MP +70. -->
		<passive_skill id="54047" level="4" /> <!-- Talisman: Aden Talisman +3 -->
	</option>
	<option id="33342" name="Talisman of Aden">
		<!-- P. Def. +20\nM. Def. +30\nAtk. Spd. +20\nCasting Spd. +20\nMax HP +180\nMax MP +100\nAcquired XP/SP +10% -->
		<passive_skill id="54047" level="5" /> <!-- Talisman: Aden Talisman +4 -->
	</option>
	<option id="33343" name="Talisman of Aden">
		<!-- P. Atk. +50\nM. Atk. +100\nP. Def. +30\nM. Def. +40\nAtk. Spd. +25\nCasting Spd. +25\nMax HP +220\nMax MP +130\nXP/SP Gain +15% -->
		<passive_skill id="54047" level="6" /> <!-- Talisman: Aden Talisman +5 -->
	</option>
	<option id="33344" name="Talisman of Aden">
		<!-- P. Atk. +80\nM. Atk. +150\nP. Def. +40\nM. Def. +60\nAtk. Spd. +40\nCasting Spd. +45\nMax HP +260\nMax MP +160\nXP/SP Gain +20% -->
		<passive_skill id="54047" level="7" /> <!-- Talisman: Aden Talisman +6 -->
	</option>
	<option id="33345" name="Talisman of Aden">
		<!-- P. Atk. +135\nM. Atk. +250\nP. Def. +60\nM. Def. +80\nAtk. Spd. +70\nCasting Spd. +75\nMax HP +520\nMax MP +320\nXP/SP Gain +50% -->
		<passive_skill id="54047" level="8" /> <!-- Talisman: Aden Talisman +7 -->
	</option>
	<option id="33346" name="Talisman of Aden">
		<!-- P. Atk. +180\nM. Atk. +360\nP. Def. +80\nM. Def. +120\nAtk. Spd. +80\nCasting Spd. +95\nMax HP +640\nMax MP +360\nXP/SP Gain +50% -->
		<passive_skill id="54047" level="9" /> <!-- Talisman: Aden Talisman +8 -->
	</option>
	<option id="33347" name="Talisman of Aden">
		<!-- P. Atk. +225\nM. Atk. +420\nP. Def. +120\nM. Def. +160\nAtk. Spd. +90\nCasting Spd. +110\nMax HP +910\nMax MP +430\nXP/SP Gain +50% -->
		<passive_skill id="54047" level="10" /> <!-- Talisman: Aden Talisman +9 -->
	</option>
	<option id="33348" name="Talisman of Aden">
		<!-- P. Atk. +270\nM. Atk. +490\nP. Def. +160\nM. Def. +200\nAtk. Spd. +100\nCasting Spd. +125\nMax HP +1120\nMax MP +530\nXP/SP Gain +50% -->
		<passive_skill id="54047" level="11" /> <!-- Talisman: Aden Talisman +10 -->
	</option>
	<option id="33349" name="option_id_33349">
		<!-- Can use a skill to recover Sayha's Blessing. -->
	</option>
	<option id="33350" name="option_id_33350">
		<!-- Can use a skill to recover Sayha's Blessing. -->
	</option>
	<option id="33351" name="option_id_33351">
		<!-- Can use a skill to recover Sayha's Blessing. -->
	</option>
	<option id="33352" name="option_id_33352">
		<!-- Can use a skill to recover Sayha's Blessing. -->
	</option>
	<option id="33353" name="option_id_33353">
		<!-- Can use a skill to recover Sayha's Blessing. -->
	</option>
	<option id="33354" name="option_id_33354">
		<!-- Can use a skill to recover Sayha's Blessing. -->
	</option>
	<option id="33355" name="option_id_33355">
		<!-- Can use a skill to recover Sayha's Blessing. -->
	</option>
	<option id="33356" name="option_id_33356">
		<!-- Can use a skill to recover Sayha's Blessing. -->
	</option>
	<option id="33357" name="option_id_33357">
		<!-- Can use a skill to recover Sayha's Blessing. -->
	</option>
	<option id="33358" name="option_id_33358">
		<!-- Can use a skill to recover Sayha's Blessing. -->
	</option>
	<option id="33359" name="Dragon_Belt">
		<!-- Weight Limit +1000\nDEX, WIT +1. -->
		<passive_skill id="54082" level="1" /> <!-- Belt: Dragon's Belt -->
	</option>
	<option id="33360" name="Dragon_Belt">
		<!-- Dragon’s Belt’s Weight Limit +2000\nInventory Slots +2\nDEX, WIT +1\nCON, MEN +1. -->
		<passive_skill id="54082" level="2" /> <!-- Belt: Dragon's Belt +1 -->
	</option>
	<option id="33361" name="Dragon_Belt">
		<!-- Weight Limit +3000\nInventory Slots +4\nDEX, WIT +1\nCON, MEN +1\nSTR, INT +1. -->
		<passive_skill id="54082" level="3" /> <!-- Belt: Dragon's Belt +2 -->
	</option>
	<option id="33362" name="Dragon_Belt">
		<!-- Weight Limit +4000\nInventory Slots +6\nDEX, WIT +2\nCON, MEN +2\nSTR, INT +2. -->
		<passive_skill id="54082" level="4" /> <!-- Belt: Dragon's Belt +3 -->
	</option>
	<option id="33363" name="Dragon_Belt">
		<!-- Weight Limit +5000\nInventory Slots +6\nMax HP +100\nMax MP +50\nMax CP +100\nDEX, WIT +3\nCON, MEN +3\nSTR, INT +3. -->
		<passive_skill id="54082" level="5" /> <!-- Belt: Dragon's Belt +4 -->
	</option>
	<option id="33364" name="Dragon_Belt">
		<!-- Weight Limit +6000\nInventory Slots +6\nMax HP +150\nMax MP +100\nMax CP +200\nHP Potion Additional Recovery +80\nMP Potion Additional Recovery +10\nP. Def. +30\nM. Def. +20\nDEX, WIT +3\nCON, MEN +4\nSTR, INT +3. -->
		<passive_skill id="54082" level="6" /> <!-- Belt: Dragon's Belt +5 -->
	</option>
	<option id="33365" name="Dragon_Belt">
		<!-- Weight Limit +7000\nInventory Slots +6\nMax HP +200\nMax MP +150\nMax CP +300\nHP Potion Additional Recovery +100\nMP Potion Additional Recovery +20\nP. Def. +40\nM. Def. +30\nDEX, WIT +4\nCON, MEN +4\nSTR, INT +3. -->
		<passive_skill id="54082" level="7" /> <!-- Belt: Dragon's Belt +6 -->
	</option>
	<option id="33366" name="Dragon_Belt">
		<!-- Weight Limit +8000\nInventory Slots +8\nMax HP +300\nMax MP +200\nMax CP +500\nHP Potion Additional Recovery +120\nMP Potion Additional Recovery +30\nP. Def. +50\nM. Def. +40\nAtk. Spd. +20\nP. Critical/M. Skill Critical Rate +10\nDEX, WIT +4\nCON, MEN +4\nSTR, INT +4. -->
		<passive_skill id="54082" level="8" /> <!-- Belt: Dragon's Belt +7 -->
	</option>
	<option id="33367" name="Dragon_Belt">
		<!-- Weight Limit +9000\nInventory Slots +8\nMax HP +400\nMax MP +250\nMax CP +700\nHP Potion Additional Recovery +150\nMP Potion Additional Recovery +50\nP. Def. +80\nM. Def. +50\nAtk. Spd. +30\nP. Critical/M. Skill Critical Rate +20\nHeal Received +5%\nDamage Received -3%\nDEX, WIT +4\nCON, MEN +5\nSTR, INT +4. -->
		<passive_skill id="54082" level="9" /> <!-- Belt: Dragon's Belt +8 -->
	</option>
	<option id="33368" name="Dragon_Belt">
		<!-- Weight Limit +10000\nInventory Slots +10\nMax HP +600\nMax MP +300\nMax CP +1000\nHP Potion Additional Recovery +200\nMP Potion Additional Recovery +80\nP. Def. +100\nM. Def. +80\nAtk. Spd. +50\nP. Critical/M. Skill Critical Rate +30\nHeal Received +10%\nDamage Received -5%\nDEX, WIT +5\nCON, MEN +5\nSTR, INT +4. -->
		<passive_skill id="54082" level="10" /> <!-- Belt: Dragon's Belt +9 -->
	</option>
	<option id="33369" name="Dragon_Belt">
		<!-- Weight Limit +12000\nInventory Slots +12\nMax HP +1000\nMax MP +500\nMax CP +1500\nHP Potion Additional Recovery +300\nMP Potion Additional Recovery +100\nP. Def. +150\nM. Def. +120\nAtk. Spd. +100\nP. Critical/M. Skill Critical Rate +50\nHeal Received +20%\nDamage Received -10%\nDEX, WIT +5\nCON, MEN +5\nSTR, INT +5. -->
		<passive_skill id="54082" level="11" /> <!-- Belt: Dragon's Belt +10 -->
	</option>
	<option id="33370" name="option_id_33370">
		<!-- P. Atk. +14, M. Atk. +22. When two or more Talismans of identical effects are equipped, the effect of only one Talisman will be applied. -->
	</option>
	<option id="33371" name="option_id_33371">
		<!-- P. Atk. +27, M. Atk. +44, M. Def. +10. When two or more Talismans of identical effects are equipped, the effect of only one Talisman will be applied. -->
	</option>
	<option id="33372" name="option_id_33372">
		<!-- P. Atk. +41, M. Atk. +66, M. Def. +20, P. Skill Power/M. Skill Power +1%, and Weapon Resistance +1. When two or more Talismans of identical effects are equipped, the effect of only one Talisman will be applied. -->
	</option>
	<option id="33373" name="option_id_33373">
		<!-- P. Atk. +68, M. Atk. +109, M. Def. +30, P. Skill Power/M. Skill Power +2%, Weapon Resistance +2, CON +1, and MEN +1. When two or more Talismans of identical effects are equipped, the effect of only one Talisman will be applied. -->
	</option>
	<option id="33374" name="option_id_33374">
		<!-- P. Atk. +170, M. Atk. +235, M. Def. +40, P. Skill Power/M. Skill Power +2%, Weapon Resistance +2, CON +1, MEN +1, STR +1, INT +1. Skill MP Consumption -2%. When two or more Talismans of identical effects are equipped, the effect of only one Talisman will be applied. -->
	</option>
	<option id="33375" name="option_id_33375">
		<!-- P. Atk. +200, M. Atk. +275, M. Def. +60, P. Skill Power/M. Skill Power +3%, Weapon Resistance +3, CON +1, MEN +1, STR +1, INT +1, P. Critical/M. Critical Rate +10. Skill MP Consumption -4%. When two or more Talismans of identical effects are equipped, the effect of only one Talisman will be applied. -->
	</option>
	<option id="33376" name="Ring_of_Insolence">
		<!-- Sleep Resistance +1%. -->
		<passive_skill id="50189" level="1" /> <!-- Ring: Ring of Insolence -->
	</option>
	<option id="33377" name="Ring_of_Insolence">
		<!-- Sleep Resistance +2%. -->
		<passive_skill id="50189" level="2" /> <!-- Ring: Ring of Insolence -->
	</option>
	<option id="33378" name="Ring_of_Insolence">
		<!-- Sleep Resistance +3%. -->
		<passive_skill id="50189" level="3" /> <!-- Ring: Ring of Insolence -->
	</option>
	<option id="33379" name="Ring_of_Insolence">
		<!-- Sleep Resistance +4%. -->
		<passive_skill id="50189" level="4" /> <!-- Ring: Ring of Insolence -->
	</option>
	<option id="33380" name="Ring_of_Insolence">
		<!-- Sleep Resistance +5%. -->
		<passive_skill id="50189" level="5" /> <!-- Ring: Ring of Insolence -->
	</option>
	<option id="33381" name="Ring_of_Insolence">
		<!-- Sleep Resistance +10%\nMax HP +100\nP. Atk. +10\nM. Atk. +10 -->
		<passive_skill id="50189" level="6" /> <!-- Ring: Ring of Insolence -->
	</option>
	<option id="33382" name="Ring_of_Insolence">
		<!-- Sleep Resistance +12%\nMax HP +150\nP. Atk. +15\nM. Atk. +15 -->
		<passive_skill id="50189" level="7" /> <!-- Ring: Ring of Insolence -->
	</option>
	<option id="33383" name="Ring_of_Insolence">
		<!-- CON +1\nSleep Resistance +14%\nMax HP +200\nP. Atk. +20\nM. Atk. +20 -->
		<passive_skill id="50189" level="8" /> <!-- Ring: Ring of Insolence -->
	</option>
	<option id="33384" name="Ring_of_Insolence">
		<!-- CON +1\nSleep Resistance +18%\nMax HP +250\nP. Atk. +30\nM. Atk. +30 -->
		<passive_skill id="50189" level="9" /> <!-- Ring: Ring of Insolence -->
	</option>
	<option id="33385" name="Ring_of_Insolence">
		<!-- CON +2\nSleep Resistance +22%\nMax HP +250\nP. Atk. +50\nM. Atk. +50 -->
		<passive_skill id="50189" level="10" /> <!-- Ring: Ring of Insolence -->
	</option>
	<option id="33386" name="Ring_of_Insolence">
		<!-- CON +5\nSTR +1\nINT +1\nSleep Resistance +30%\nMax HP +1000\nP. Atk. +300\nM. Atk. +300 -->
		<passive_skill id="50189" level="11" /> <!-- Ring: Ring of Insolence -->
	</option>
	<option id="33387" name="Dragon_Valley_Earring">
		<!-- Stun Attack Resistance +1%. -->
		<passive_skill id="50190" level="1" /> <!-- Earring: Earring of Dragon World -->
	</option>
	<option id="33388" name="Dragon_Valley_Earring">
		<!-- Stun Attack Resistance +2%. -->
		<passive_skill id="50190" level="2" /> <!-- Earring: Earring of Dragon World -->
	</option>
	<option id="33389" name="Dragon_Valley_Earring">
		<!-- Stun Attack Resistance +3%. -->
		<passive_skill id="50190" level="3" /> <!-- Earring: Earring of Dragon World -->
	</option>
	<option id="33390" name="Dragon_Valley_Earring">
		<!-- Stun Attack Resistance +4%. -->
		<passive_skill id="50190" level="4" /> <!-- Earring: Earring of Dragon World -->
	</option>
	<option id="33391" name="Dragon_Valley_Earring">
		<!-- Stun Attack Resistance +5%. -->
		<passive_skill id="50190" level="5" /> <!-- Earring: Earring of Dragon World -->
	</option>
	<option id="33392" name="Dragon_Valley_Earring">
		<!-- Stun Attack Resistance +10%.\nMax MP +100\nAtk. Spd. +5\nCasting Spd. +5 -->
		<passive_skill id="50190" level="6" /> <!-- Earring: Earring of Dragon World -->
	</option>
	<option id="33393" name="Dragon_Valley_Earring">
		<!-- Stun Attack Resistance +12%.\nMax MP +150\nAtk. Spd. +7\nCasting Spd. +7 -->
		<passive_skill id="50190" level="7" /> <!-- Earring: Earring of Dragon World -->
	</option>
	<option id="33394" name="Dragon_Valley_Earring">
		<!-- MEN +1\nStun Attack Resistance +14%.\nMax MP +200\nAtk. Spd. +10\nCasting Spd. +10 -->
		<passive_skill id="50190" level="8" /> <!-- Earring: Earring of Dragon World -->
	</option>
	<option id="33395" name="Dragon_Valley_Earring">
		<!-- MEN +1\nStun Attack Resistance +18%.\nMax MP +250\nAtk. Spd. +15\nCasting Spd. +15 -->
		<passive_skill id="50190" level="9" /> <!-- Earring: Earring of Dragon World -->
	</option>
	<option id="33396" name="Dragon_Valley_Earring">
		<!-- MEN +2\nStun Attack Resistance +22%.\nMax MP +250\nAtk. Spd. +40\nCasting Spd. +40 -->
		<passive_skill id="50190" level="10" /> <!-- Earring: Earring of Dragon World -->
	</option>
	<option id="33397" name="Dragon_Valley_Earring">
		<!-- MEN +5\nDEX +1\nWIT +1\nStun Attack Resistance +30%.\nMax MP +1000\nAtk. Spd. +150\nCasting Spd. +150 -->
		<passive_skill id="50190" level="11" /> <!-- Earring: Earring of Dragon World -->
	</option>
	<option id="33398" name="option_id_33398">
	</option>
	<option id="33399" name="option_id_33399">
		<!-- P. Atk. +16, M. Atk. +23, CON/MEN +1, Skill Cooldown -1% -->
	</option>
</list>
